samplingresourcemonitor/__init__.py
samplingresourcemonitor-0.1.dist-info/LICENSE
samplingresourcemonitor-0.1.dist-info/METADATA
samplingresourcemonitor-0.1.dist-info/WHEEL
samplingresourcemonitor-0.1.dist-info/top_level.txt
samplingresourcemonitor-0.1.dist-info/RECORD
